{
  "last_node_id": 32,
  "last_link_id": 66,
  "nodes": [
    {
      "id": 5,
      "type": "EmptyLatentImage",
      "pos": [
        439,
        895
      ],
      "size": {
        "0": 315,
        "1": 106
      },
      "flags": {},
      "order": 0,
      "mode": 0,
      "outputs": [
        {
          "name": "LATENT",
          "type": "LATENT",
          "links": [
            19
          ],
          "slot_index": 0
        }
      ],
      "properties": {
        "Node name for S&R": "EmptyLatentImage"
      },
      "widgets_values": [
        512,
        768,
        1
      ]
    },
    {
      "id": 28,
      "type": "ControlNetLoader",
      "pos": [
        795,
        63
      ],
      "size": {
        "0": 315,
        "1": 58
      },
      "flags": {},
      "order": 1,
      "mode": 0,
      "outputs": [
        {
          "name": "CONTROL_NET",
          "type": "CONTROL_NET",
          "links": [
            54
          ],
          "shape": 3
        }
      ],
      "properties": {
        "Node name for S&R": "ControlNetLoader"
      },
      "widgets_values": [
        "control_v11f1p_sd15_depth_fp16.safetensors"
      ]
    },
    {
      "id": 19,
      "type": "LoraLoader",
      "pos": [
        48,
        672
      ],
      "size": {
        "0": 315,
        "1": 126
      },
      "flags": {},
      "order": 4,
      "mode": 0,
      "inputs": [
        {
          "name": "model",
          "type": "MODEL",
          "link": 32
        },
        {
          "name": "clip",
          "type": "CLIP",
          "link": 59
        }
      ],
      "outputs": [
        {
          "name": "MODEL",
          "type": "MODEL",
          "links": [
            36
          ],
          "shape": 3,
          "slot_index": 0
        },
        {
          "name": "CLIP",
          "type": "CLIP",
          "links": [
            34,
            60
          ],
          "shape": 3,
          "slot_index": 1
        }
      ],
      "properties": {
        "Node name for S&R": "LoraLoader"
      },
      "widgets_values": [
        "LCM_LoRA_Weights_SD15.safetensors",
        1,
        1
      ]
    },
    {
      "id": 8,
      "type": "VAEDecode",
      "pos": [
        1031,
        365
      ],
      "size": {
        "0": 210,
        "1": 46
      },
      "flags": {},
      "order": 12,
      "mode": 0,
      "inputs": [
        {
          "name": "samples",
          "type": "LATENT",
          "link": 41
        },
        {
          "name": "vae",
          "type": "VAE",
          "link": 8
        }
      ],
      "outputs": [
        {
          "name": "IMAGE",
          "type": "IMAGE",
          "links": [
            55
          ],
          "slot_index": 0
        }
      ],
      "properties": {
        "Node name for S&R": "VAEDecode"
      }
    },
    {
      "id": 22,
      "type": "VAEDecode",
      "pos": [
        1717,
        571
      ],
      "size": {
        "0": 210,
        "1": 46
      },
      "flags": {},
      "order": 13,
      "mode": 0,
      "inputs": [
        {
          "name": "samples",
          "type": "LATENT",
          "link": 46
        },
        {
          "name": "vae",
          "type": "VAE",
          "link": 47
        }
      ],
      "outputs": [
        {
          "name": "IMAGE",
          "type": "IMAGE",
          "links": [
            61
          ],
          "shape": 3,
          "slot_index": 0
        }
      ],
      "properties": {
        "Node name for S&R": "VAEDecode"
      }
    },
    {
      "id": 4,
      "type": "CheckpointLoaderSimple",
      "pos": [
        36,
        939
      ],
      "size": {
        "0": 315,
        "1": 98
      },
      "flags": {},
      "order": 2,
      "mode": 0,
      "outputs": [
        {
          "name": "MODEL",
          "type": "MODEL",
          "links": [
            32,
            62
          ],
          "slot_index": 0
        },
        {
          "name": "CLIP",
          "type": "CLIP",
          "links": [
            59
          ],
          "slot_index": 1
        },
        {
          "name": "VAE",
          "type": "VAE",
          "links": [
            8,
            47
          ],
          "slot_index": 2
        }
      ],
      "properties": {
        "Node name for S&R": "CheckpointLoaderSimple"
      },
      "widgets_values": [
        "epicrealism_naturalSinRC1VAE.safetensors"
      ]
    },
    {
      "id": 26,
      "type": "PreviewImage",
      "pos": [
        439,
        30
      ],
      "size": {
        "0": 210,
        "1": 246
      },
      "flags": {},
      "order": 8,
      "mode": 0,
      "inputs": [
        {
          "name": "images",
          "type": "IMAGE",
          "link": 66
        }
      ],
      "properties": {
        "Node name for S&R": "PreviewImage"
      }
    },
    {
      "id": 24,
      "type": "LoadImage",
      "pos": [
        57,
        139
      ],
      "size": {
        "0": 315,
        "1": 314
      },
      "flags": {},
      "order": 3,
      "mode": 0,
      "outputs": [
        {
          "name": "IMAGE",
          "type": "IMAGE",
          "links": [
            64
          ],
          "shape": 3,
          "slot_index": 0
        },
        {
          "name": "MASK",
          "type": "MASK",
          "links": null,
          "shape": 3
        }
      ],
      "properties": {
        "Node name for S&R": "LoadImage"
      },
      "widgets_values": [
        "ComfyUI_00627_ (1).png",
        "image"
      ]
    },
    {
      "id": 32,
      "type": "CannyEdgePreprocessor",
      "pos": [
        441,
        264
      ],
      "size": [
        290.89998539027386,
        112.4850279372771
      ],
      "flags": {},
      "order": 5,
      "mode": 0,
      "inputs": [
        {
          "name": "image",
          "type": "IMAGE",
          "link": 64
        }
      ],
      "outputs": [
        {
          "name": "IMAGE",
          "type": "IMAGE",
          "links": [
            65,
            66
          ],
          "shape": 3,
          "slot_index": 0
        }
      ],
      "properties": {
        "Node name for S&R": "CannyEdgePreprocessor"
      },
      "widgets_values": [
        100,
        200,
        512
      ]
    },
    {
      "id": 29,
      "type": "SaveImage",
      "pos": [
        1289,
        45
      ],
      "size": [
        320.6820643401343,
        399.15094722401
      ],
      "flags": {},
      "order": 14,
      "mode": 0,
      "inputs": [
        {
          "name": "images",
          "type": "IMAGE",
          "link": 55
        }
      ],
      "properties": {},
      "widgets_values": [
        "ComfyUI"
      ]
    },
    {
      "id": 31,
      "type": "SaveImage",
      "pos": [
        1680,
        51
      ],
      "size": [
        335.20899177875845,
        401.07216629725946
      ],
      "flags": {},
      "order": 15,
      "mode": 0,
      "inputs": [
        {
          "name": "images",
          "type": "IMAGE",
          "link": 61
        }
      ],
      "properties": {},
      "widgets_values": [
        "ComfyUI"
      ]
    },
    {
      "id": 27,
      "type": "ControlNetApply",
      "pos": [
        829.7553611755371,
        186.10625610351565
      ],
      "size": {
        "0": 317.4000244140625,
        "1": 98
      },
      "flags": {},
      "order": 9,
      "mode": 0,
      "inputs": [
        {
          "name": "conditioning",
          "type": "CONDITIONING",
          "link": 52
        },
        {
          "name": "control_net",
          "type": "CONTROL_NET",
          "link": 54,
          "slot_index": 1
        },
        {
          "name": "image",
          "type": "IMAGE",
          "link": 65
        }
      ],
      "outputs": [
        {
          "name": "CONDITIONING",
          "type": "CONDITIONING",
          "links": [
            53
          ],
          "shape": 3,
          "slot_index": 0
        }
      ],
      "properties": {
        "Node name for S&R": "ControlNetApply"
      },
      "widgets_values": [
        0.5
      ]
    },
    {
      "id": 15,
      "type": "KSampler",
      "pos": [
        940,
        495
      ],
      "size": {
        "0": 312.2738952636719,
        "1": 527.7344970703125
      },
      "flags": {},
      "order": 10,
      "mode": 0,
      "inputs": [
        {
          "name": "model",
          "type": "MODEL",
          "link": 36
        },
        {
          "name": "positive",
          "type": "CONDITIONING",
          "link": 53
        },
        {
          "name": "negative",
          "type": "CONDITIONING",
          "link": 18
        },
        {
          "name": "latent_image",
          "type": "LATENT",
          "link": 19
        }
      ],
      "outputs": [
        {
          "name": "LATENT",
          "type": "LATENT",
          "links": [
            40,
            41
          ],
          "shape": 3,
          "slot_index": 0
        }
      ],
      "properties": {
        "Node name for S&R": "KSampler"
      },
      "widgets_values": [
        1074776189553149,
        "randomize",
        8,
        2,
        "lcm",
        "karras",
        1
      ]
    },
    {
      "id": 20,
      "type": "KSampler",
      "pos": [
        1354,
        533
      ],
      "size": {
        "0": 315,
        "1": 474
      },
      "flags": {},
      "order": 11,
      "mode": 0,
      "inputs": [
        {
          "name": "model",
          "type": "MODEL",
          "link": 62
        },
        {
          "name": "positive",
          "type": "CONDITIONING",
          "link": 43
        },
        {
          "name": "negative",
          "type": "CONDITIONING",
          "link": 44
        },
        {
          "name": "latent_image",
          "type": "LATENT",
          "link": 40
        }
      ],
      "outputs": [
        {
          "name": "LATENT",
          "type": "LATENT",
          "links": [
            46
          ],
          "shape": 3,
          "slot_index": 0
        }
      ],
      "properties": {
        "Node name for S&R": "KSampler"
      },
      "widgets_values": [
        736491803700776,
        "randomize",
        6,
        9,
        "dpmpp_2m",
        "karras",
        0.4
      ]
    },
    {
      "id": 7,
      "type": "CLIPTextEncode",
      "pos": [
        390,
        672
      ],
      "size": {
        "0": 425.27801513671875,
        "1": 180.6060791015625
      },
      "flags": {},
      "order": 7,
      "mode": 0,
      "inputs": [
        {
          "name": "clip",
          "type": "CLIP",
          "link": 60
        }
      ],
      "outputs": [
        {
          "name": "CONDITIONING",
          "type": "CONDITIONING",
          "links": [
            18,
            44
          ],
          "slot_index": 0
        }
      ],
      "properties": {
        "Node name for S&R": "CLIPTextEncode"
      },
      "widgets_values": [
        "text, watermark, error, cropped, ugly, duplicate, morbid, mutilated, out of frame, extra fingers, tattoo, mutated hands, poorly drawn hands, poorly drawn face, mutation, deformed, dehydrated, bad anatomy, bad proportions, extra limbs, cloned face, disfigured, gross proportions, malformed limbs, missing arms, missing legs, extra arms, extra legs, fused fingers, too many fingers, long neck, username, watermark, signature"
      ]
    },
    {
      "id": 6,
      "type": "CLIPTextEncode",
      "pos": [
        457,
        450
      ],
      "size": {
        "0": 422.84503173828125,
        "1": 164.31304931640625
      },
      "flags": {},
      "order": 6,
      "mode": 0,
      "inputs": [
        {
          "name": "clip",
          "type": "CLIP",
          "link": 34
        }
      ],
      "outputs": [
        {
          "name": "CONDITIONING",
          "type": "CONDITIONING",
          "links": [
            43,
            52
          ],
          "slot_index": 0
        }
      ],
      "properties": {
        "Node name for S&R": "CLIPTextEncode"
      },
      "widgets_values": [
        "((((little,girl)))),(short kid),infant,((skinny,petite)),(((child))),young,((6 year)),solo, long hair, ((baby clothes)),short dress,(((slutty expression))),((right arm behind head)),((long wet hair on left side)),((small feet)), realisitic,uncensored, full body, ((squating)),((pussy)),(naked lower body), spreading leg, ((tip toes)), black hair, outdoors, shiny skin, sharp focus,hyper detailed,photo real,blurry background, realistic, wet hair"
      ]
    }
  ],
  "links": [
    [
      8,
      4,
      2,
      8,
      1,
      "VAE"
    ],
    [
      18,
      7,
      0,
      15,
      2,
      "CONDITIONING"
    ],
    [
      19,
      5,
      0,
      15,
      3,
      "LATENT"
    ],
    [
      32,
      4,
      0,
      19,
      0,
      "MODEL"
    ],
    [
      34,
      19,
      1,
      6,
      0,
      "CLIP"
    ],
    [
      36,
      19,
      0,
      15,
      0,
      "MODEL"
    ],
    [
      40,
      15,
      0,
      20,
      3,
      "LATENT"
    ],
    [
      41,
      15,
      0,
      8,
      0,
      "LATENT"
    ],
    [
      43,
      6,
      0,
      20,
      1,
      "CONDITIONING"
    ],
    [
      44,
      7,
      0,
      20,
      2,
      "CONDITIONING"
    ],
    [
      46,
      20,
      0,
      22,
      0,
      "LATENT"
    ],
    [
      47,
      4,
      2,
      22,
      1,
      "VAE"
    ],
    [
      52,
      6,
      0,
      27,
      0,
      "CONDITIONING"
    ],
    [
      53,
      27,
      0,
      15,
      1,
      "CONDITIONING"
    ],
    [
      54,
      28,
      0,
      27,
      1,
      "CONTROL_NET"
    ],
    [
      55,
      8,
      0,
      29,
      0,
      "IMAGE"
    ],
    [
      59,
      4,
      1,
      19,
      1,
      "CLIP"
    ],
    [
      60,
      19,
      1,
      7,
      0,
      "CLIP"
    ],
    [
      61,
      22,
      0,
      31,
      0,
      "IMAGE"
    ],
    [
      62,
      4,
      0,
      20,
      0,
      "MODEL"
    ],
    [
      64,
      24,
      0,
      32,
      0,
      "IMAGE"
    ],
    [
      65,
      32,
      0,
      27,
      2,
      "IMAGE"
    ],
    [
      66,
      32,
      0,
      26,
      0,
      "IMAGE"
    ]
  ],
  "groups": [],
  "config": {},
  "extra": {},
  "version": 0.4
}